ds_store_dump/DSStoreDumper.py
ds_store_dump/__init__.py
ds_store_dump/__main__.py
ds_store_dump/cli.py
ds_store_dump/log.py
ds_store_dump/utils/decorators.py
ds_store_dump/utils/logging.py
ds_store_dump/utils/termcolors.py
ds_store_dump-0.1.2.dist-info/entry_points.txt
ds_store_dump-0.1.2.dist-info/LICENSE
ds_store_dump-0.1.2.dist-info/WHEEL
ds_store_dump-0.1.2.dist-info/METADATA
ds_store_dump-0.1.2.dist-info/RECORD
