Metadata-Version: 2.1
Name: ds-store-dump
Version: 0.1.2
Summary: Dump backups and another files using .DS_Store
License: MIT
Author: tz4678
Author-email: tz4678@gmail.com
Requires-Python: >=3.10,<4.0
Classifier: License :: OSI Approved :: MIT License
Classifier: Programming Language :: Python :: 3
Classifier: Programming Language :: Python :: 3.10
Requires-Dist: aiodns (>=3.0.0,<4.0.0)
Requires-Dist: aiohttp (>=3.8.1,<4.0.0)
Requires-Dist: cchardet (>=2.1.7,<3.0.0)
Requires-Dist: click (>=8.1.3,<9.0.0)
Requires-Dist: ds-store (>=1.3.0,<2.0.0)
